{"version": 0.6, "generator": "Overpass API 0.7.62.5 1bd436f1", "osm3s": {"timestamp_osm_base": "2025-04-23T12:45:45Z", "copyright": "The data included in this document is from www.openstreetmap.org. The data is made available under ODbL."}, "elements": [{"type": "node", "id": 3891122769, "lat": 49.4456767, "lon": 1.0870573, "tags": {"bench": "yes", "bin": "no", "bus": "yes", "covered": "yes", "highway": "bus_stop", "name": "Cauchoise", "public_transport": "platform", "shelter": "yes", "tactile_paving": "no"}}, {"type": "node", "id": 3891698564, "lat": 49.4461098, "lon": 1.087257, "tags": {"bench": "yes", "bin": "yes", "bus": "yes", "check_date:bench": "2024-09-22", "covered": "no", "departures_board": "yes", "highway": "bus_stop", "lit": "yes", "name": "Cauchoise", "public_transport": "platform", "shelter": "yes", "tactile_paving": "yes", "wheelchair": "yes"}}, {"type": "node", "id": 5713877177, "lat": 49.445488, "lon": 1.0875457, "tags": {"bench": "yes", "bin": "no", "bus": "yes", "highway": "bus_stop", "lit": "no", "name": "Cauchoise", "public_transport": "platform", "shelter": "yes", "tactile_paving": "no"}}, {"type": "node", "id": 6491923941, "lat": 49.4459049, "lon": 1.0873691, "tags": {"bench": "yes", "bin": "yes", "bus": "yes", "covered": "no", "departures_board": "yes", "highway": "bus_stop", "lit": "yes", "name": "Cauchoise", "public_transport": "platform", "shelter": "yes", "tactile_paving": "yes", "wheelchair": "yes"}}]}